broadie/__init__.py
broadie/__main__.py
broadie/_version.py
broadie/agents.py
broadie/channels.py
broadie/cli.py
broadie/config.py
broadie/decorators.py
broadie/factory.py
broadie/graph_builder.py
broadie/mixins.py
broadie/prompts.py
broadie/py.typed
broadie/schemas.py
broadie/tracing.py
broadie/utils.py
broadie/a2a/__init__.py
broadie/a2a/register.py
broadie/a2a/routes.py
broadie/a2a/utils.py
broadie/persistence/__init__.py
broadie/persistence/database.py
broadie/persistence/manager.py
broadie/persistence/mixins.py
broadie/persistence/models.py
broadie/persistence/repository.py
broadie/persistence/migrations/README
broadie/persistence/migrations/env.py
broadie/persistence/migrations/script.py.mako
broadie/persistence/migrations/versions/20251004_1031_e9d7edf701e1_.py
broadie/server/__init__.py
broadie/server/app.py
broadie/server/credentials.py
broadie/tools/__init__.py
broadie/tools/channels.py
broadie/tools/memory.py
broadie/tools/tasks.py
broadie-2.1.1.dist-info/licenses/LICENSE
broadie-2.1.1.dist-info/METADATA
broadie-2.1.1.dist-info/WHEEL
broadie-2.1.1.dist-info/entry_points.txt
broadie-2.1.1.dist-info/top_level.txt
broadie-2.1.1.dist-info/RECORD
