Metadata-Version: 2.4
Name: broadie
Version: 2.1.1
Summary: Broadie: Opinionated framework for building and serving AI agents with build on LangGraph + LangServe.
Author-email: Broad Institute <broadie@broadinstitute.org>
License-Expression: MIT AND (Apache-2.0 OR BSD-2-Clause)
Project-URL: Homepage, https://github.com/broadinstitute/broadie
Project-URL: Repository, https://github.com/broadinstitute/broadie
Project-URL: Documentation, https://broadie.readthedocs.io
Project-URL: Issues, https://github.com/broadinstitute/broadie/issues
Classifier: Development Status :: 3 - Alpha
Classifier: Intended Audience :: Developers
Classifier: Programming Language :: Python :: 3
Classifier: Programming Language :: Python :: 3.10
Classifier: Programming Language :: Python :: 3.11
Classifier: Programming Language :: Python :: 3.12
Classifier: Topic :: Software Development :: Libraries :: Python Modules
Classifier: Topic :: Scientific/Engineering :: Artificial Intelligence
Requires-Python: >=3.10
License-File: LICENSE
Requires-Dist: langchain-google-vertexai>=2.1.2
Requires-Dist: fastapi>=0.116.1
Requires-Dist: langgraph-checkpoint-postgres>=2.0.23
Requires-Dist: langgraph>=0.6.6
Requires-Dist: python-dotenv>=1.1.1
Requires-Dist: langgraph-checkpoint-sqlite>=2.0.11
Requires-Dist: click>=8.1.8
Requires-Dist: uvicorn>=0.35.0
Requires-Dist: slack-sdk>=3.36.0
Requires-Dist: a2a-sdk>=0.3.3
Requires-Dist: asyncpg>=0.30.0
Requires-Dist: aiohttp>=3.12.15
Requires-Dist: aiosmtplib>=4.0.2
Requires-Dist: pydantic-settings>=2.10.1
Requires-Dist: sse-starlette>=3.0.2
Requires-Dist: langchain>=0.3.27
Requires-Dist: psycopg-binary>=3.2.9
Requires-Dist: alembic>=1.16.5
Requires-Dist: langgraph-swarm>=0.0.14
Requires-Dist: greenlet>=3.2.4
Requires-Dist: slowapi>=0.1.9
Requires-Dist: langgraph-supervisor>=0.0.29
Provides-Extra: dev
Requires-Dist: ruff==0.12.11; extra == "dev"
Requires-Dist: pytest==8.4.1; extra == "dev"
Requires-Dist: pytest-asyncio==1.1.0; extra == "dev"
Requires-Dist: pre-commit==3.0.0; extra == "dev"
Requires-Dist: httpx==0.27.0; extra == "dev"
Dynamic: license-file
